MANIFEST.in
script
setup.py
Bibtex_Difference_Checker.egg-info/PKG-INFO
Bibtex_Difference_Checker.egg-info/SOURCES.txt
Bibtex_Difference_Checker.egg-info/dependency_links.txt
Bibtex_Difference_Checker.egg-info/not-zip-safe
Bibtex_Difference_Checker.egg-info/requires.txt
Bibtex_Difference_Checker.egg-info/top_level.txt
bibtex_diff_checker/controller.py
bibtex_diff_checker/model.py
bibtex_diff_checker/test_controller.py
bibtex_diff_checker/test_model.py
bibtex_diff_checker/view.py